{"type":"View","props":{"width":720,"top":0,"right":0,"left":0,"height":1280,"bottom":0},"compId":2,"child":[{"type":"Image","props":{"top":0,"skin":"Date/bj.png","right":0,"left":0,"bottom":0},"compId":3},{"type":"Box","props":{"width":720,"height":1280,"centerY":0,"centerX":0},"compId":4,"child":[{"type":"Image","props":{"y":134,"x":0,"skin":"Date/字.png"},"compId":5},{"type":"Image","props":{"y":720,"x":359,"width":365,"var":"man","skin":"Date/矩形 2.png","name":"man","height":502,"anchorY":0.5,"anchorX":0.5},"compId":6,"child":[{"type":"Image","props":{"width":353,"skin":"Collection/di.png","height":491},"compId":7},{"type":"Image","props":{"width":365,"var":"icon","skin":"Cloth/ManIcon/5001.png","name":"icon","height":502,"centerY":0,"centerX":0},"compId":8},{"type":"Image","props":{"y":408,"x":3,"width":359,"skin":"Date/矩形 3.png","height":90},"compId":9},{"type":"Label","props":{"y":453,"x":176,"var":"name","valign":"middle","text":"肖班","name":"name","fontSize":35,"font":"SimHei","color":"#ffffff","bold":true,"anchorY":0.5,"anchorX":0.5,"align":"center"},"compId":11},{"type":"Box","props":{"y":356,"x":97,"name":"Box"},"compId":28,"child":[{"type":"Image","props":{"y":0,"x":120,"skin":"Date/形状 3.png","name":"1"},"compId":30},{"type":"Image","props":{"y":0,"x":80,"skin":"Date/形状 3.png","name":"2"},"compId":31},{"type":"Image","props":{"y":0,"x":40,"skin":"Date/形状 3.png","name":"3"},"compId":32},{"type":"Image","props":{"skin":"Date/形状 3.png","name":"4"},"compId":33}]},{"type":"Box","props":{"y":363,"x":99,"var":"StarBox","name":"StarBox"},"compId":29,"child":[{"type":"Image","props":{"y":0,"x":120,"skin":"Collection/star.png","name":"1"},"compId":34},{"type":"Image","props":{"y":0,"x":80,"skin":"Collection/star.png","name":"2"},"compId":35},{"type":"Image","props":{"y":0,"x":40,"skin":"Collection/star.png","name":"3"},"compId":36},{"type":"Image","props":{"skin":"Collection/star.png","name":"4"},"compId":37}]}]},{"type":"Image","props":{"y":1100,"x":248.5,"var":"BackBtn","skin":"Date/组 4.png","name":"BackBtn"},"compId":23}]}],"animations":[{"nodes":[{"target":5,"keyframes":{"y":[{"value":-179,"tweenMethod":"linearNone","tween":true,"target":5,"key":"y","index":0},{"value":108,"tweenMethod":"linearNone","tween":true,"target":5,"key":"y","index":60}],"x":[{"value":0,"tweenMethod":"linearNone","tween":true,"target":5,"key":"x","index":0},{"value":0,"tweenMethod":"linearNone","tween":true,"target":5,"key":"x","index":60}],"alpha":[{"value":0,"tweenMethod":"linearNone","tween":true,"target":5,"key":"alpha","index":0},{"value":1,"tweenMethod":"linearNone","tween":true,"target":5,"key":"alpha","index":60}]}},{"target":23,"keyframes":{"alpha":[{"value":0,"tweenMethod":"linearNone","tween":true,"target":23,"key":"alpha","index":0},{"value":1,"tweenMethod":"linearNone","tween":true,"target":23,"key":"alpha","index":60}]}},{"target":6,"keyframes":{"scaleX":[{"value":0,"tweenMethod":"linearNone","tween":true,"target":6,"key":"scaleX","index":0},{"value":1,"tweenMethod":"linearNone","tween":true,"target":6,"key":"scaleX","index":60}]}}],"name":"SucceedAni","id":1,"frameRate":60,"action":0}],"loadList":["Date/bj.png","Date/字.png","Date/矩形 2.png","Collection/di.png","Cloth/ManIcon/5001.png","Date/矩形 3.png","Date/形状 3.png","Collection/star.png","Date/组 4.png"],"loadList3D":[]}